coherent/licensed/__init__.py
coherent/licensed/_functools.py
coherent/licensed/setuptools.py
coherent_licensed-0.5.2.dist-info/entry_points.txt
coherent_licensed-0.5.2.dist-info/licenses/LICENSE
coherent_licensed-0.5.2.dist-info/WHEEL
coherent_licensed-0.5.2.dist-info/METADATA
coherent_licensed-0.5.2.dist-info/RECORD
