Metadata-Version: 2.4
Name: coherent.licensed
Version: 0.5.2
Summary: License management tooling for Coherent System and skeleton projects
Author-email: "Jason R. Coombs" <jaraco@jaraco.com>
Requires-Python: >= 3.9
License-Expression: MIT
Classifier: Development Status :: 4 - Beta
Classifier: Intended Audience :: Developers
Classifier: Programming Language :: Python :: 3
Classifier: Programming Language :: Python :: 3 :: Only
License-File: LICENSE
Project-URL: Source, https://github.com/coherent-oss/coherent.licensed
